twitter.common.quantity-0.3.11-py2.7-nspkg.pth
twitter/common/quantity/__init__.py
twitter/common/quantity/parse_simple.py
twitter.common.quantity-0.3.11.dist-info/DESCRIPTION.rst
twitter.common.quantity-0.3.11.dist-info/METADATA
twitter.common.quantity-0.3.11.dist-info/RECORD
twitter.common.quantity-0.3.11.dist-info/WHEEL
twitter.common.quantity-0.3.11.dist-info/metadata.json
twitter.common.quantity-0.3.11.dist-info/namespace_packages.txt
twitter.common.quantity-0.3.11.dist-info/top_level.txt
twitter.common.quantity-0.3.11.dist-info/zip-safe
